fluopenslide1/__init__.py
fluopenslide1/choice.py
fluopenslide1/fluopenslide.py
fluopenslide1/opening_tiles_RGB.py
fluopenslide1/opening_tiles_non_RGB.py
fluopenslide1/opening_with_pyramid_level.py
fluopenslide1/openslide_or_fluopenslide.py
fluopenslide1/position_to_tile.py
fluopenslide1/wavelength_to_color.py
fluopenslide1-0.0.1.dist-info/METADATA
fluopenslide1-0.0.1.dist-info/WHEEL
fluopenslide1-0.0.1.dist-info/top_level.txt
fluopenslide1-0.0.1.dist-info/RECORD
