Metadata-Version: 2.1
Name: fluopenslide1
Version: 0.0.1
Summary: Opening fluorescence .czi files
Home-page: UNKNOWN
Author: Louison Robach
Author-email: louison.robach@gmail.com
License: UNKNOWN
Platform: UNKNOWN
Requires-Dist: numpy
Requires-Dist: aicspylibczi
Requires-Dist: matplotlib
Requires-Dist: pathlib
Requires-Dist: aicsimageio
